patrick/__init__.py
patrick/display.py
patrick/cnn/__init__.py
patrick/cnn/faster_rcnn.py
patrick/core/__init__.py
patrick/core/value_objects.py
patrick/core/entities/__init__.py
patrick/core/entities/annotation.py
patrick/core/entities/array.py
patrick/core/entities/detection.py
patrick/core/entities/frame.py
patrick/core/entities/metadata.py
patrick/core/entities/movie.py
patrick/core/entities/tracking.py
patrick/repositories/__init__.py
patrick/repositories/factory.py
patrick/repositories/local.py
patrick/repositories/osf.py
patrick/repositories/repository.py
pattern_discovery_kit-0.2.3.dist-info/licenses/LICENSE
pattern_discovery_kit-0.2.3.dist-info/METADATA
pattern_discovery_kit-0.2.3.dist-info/WHEEL
pattern_discovery_kit-0.2.3.dist-info/top_level.txt
pattern_discovery_kit-0.2.3.dist-info/RECORD
