Metadata-Version: 2.4
Name: pattern-discovery-kit
Version: 0.2.3
Summary: Pattern Discovery Kit
Author-email: Mansour Benbakoura <mansour.benbakoura@inria.fr>
License: BSD 3-Clause License
Project-URL: Repository, https://github.com/mansour-b/pattern-discovery-kit
Requires-Python: >=3.8
License-File: LICENSE
Requires-Dist: imageio
Requires-Dist: ipykernel
Requires-Dist: matplotlib
Requires-Dist: moviepy<2
Requires-Dist: numpy
Requires-Dist: osfclient
Requires-Dist: PyYAML
Requires-Dist: torch
Requires-Dist: torchaudio
Requires-Dist: torchvision
Requires-Dist: tqdm
Provides-Extra: dev
Requires-Dist: ruff; extra == "dev"
Provides-Extra: doc
Requires-Dist: sphinx; extra == "doc"
Provides-Extra: test
Requires-Dist: pytest; extra == "test"
Requires-Dist: pytest-cov; extra == "test"
Dynamic: license-file
